mdformat_front_matters/__init__.py
mdformat_front_matters/_formatters.py
mdformat_front_matters/_helpers.py
mdformat_front_matters/mdit_plugins.py
mdformat_front_matters/plugin.py
mdformat_front_matters/py.typed
mdformat_front_matters-2.0.0.dist-info/licenses/LICENSE
mdformat_front_matters-2.0.0.dist-info/WHEEL
mdformat_front_matters-2.0.0.dist-info/entry_points.txt
mdformat_front_matters-2.0.0.dist-info/METADATA
mdformat_front_matters-2.0.0.dist-info/RECORD
