Metadata-Version: 2.4
Name: mdformat_front_matters
Version: 2.0.0
Summary: An mdformat plugin to format YAML, TOML, or JSON front matter
Keywords: markdown,markdown-it,mdformat,mdformat_plugin_template
Author: kyleking
Author-email: kyleking <dev.act.kyle@gmail.com>
License-Expression: MIT
License-File: LICENSE
Classifier: Intended Audience :: Developers
Classifier: License :: OSI Approved :: MIT License
Classifier: Programming Language :: Python :: 3
Classifier: Topic :: Software Development :: Libraries :: Python Modules
Requires-Dist: mdformat>=0.7.19
Requires-Dist: mdit-py-plugins>=0.4.1
Requires-Dist: ruamel-yaml>=0.18.16
Requires-Dist: toml>=0.10.0
Requires-Dist: pytest>=9.0.1 ; extra == 'test'
Requires-Dist: pytest-beartype>=0.2.0 ; extra == 'test'
Requires-Dist: pytest-cov>=7.0.0 ; extra == 'test'
Requires-Dist: typing-extensions>=4.15.0 ; extra == 'test'
Requires-Python: >=3.10.0
Project-URL: Bug Tracker, https://github.com/kyleking/mdformat-front-matters/issues
Project-URL: Changelog, https://github.com/kyleking/mdformat-front-matters/releases
Project-URL: homepage, https://github.com/kyleking/mdformat-front-matters
Provides-Extra: test
